libaudioverse/__init__.py
libaudioverse/_lav.py
libaudioverse/_libaudioverse.py
libaudioverse/libaudioverse.dll
libaudioverse/libsndfile-1.dll
libaudioverse-0.9.1.dist-info/DESCRIPTION.rst
libaudioverse-0.9.1.dist-info/METADATA
libaudioverse-0.9.1.dist-info/RECORD
libaudioverse-0.9.1.dist-info/WHEEL
libaudioverse-0.9.1.dist-info/metadata.json
libaudioverse-0.9.1.dist-info/top_level.txt
