Metadata-Version: 2.0
Name: libaudioverse
Version: 0.9.1
Summary: A library for 3D, environmental audio, and synthesis.
Home-page: http://github.com/camlorn/libaudioverse
Author: Austin Hicks
Author-email: camlorn@camlorn.net
License: UNKNOWN
Platform: UNKNOWN
Classifier: Development Status :: 3 - Alpha
Classifier: Intended Audience :: Developers
Classifier: Programming Language :: Python
Classifier: License :: OSI Approved :: GNU General Public License (GPL)
Classifier: License :: OSI Approved :: Mozilla Public License 2.0 (MPL 2.0)
Classifier: Topic :: Software Development :: Libraries
Requires-Dist: six
Requires-Dist: enum34; python_version <= "3.4"
